Questa/control_fsm.v
module control_fsm ( // NEXT: add an error flag mechanism for default handling
    // External inputs
    input wire clka,
    input wire clkb,
    input wire rst,

    // Internal inputs from datapath
    input wire [3:0] opcode,
    input wire zero_flag, // Rs1 - Rs2 == 0
    input wire counter_done, // 1 = 16 cycles completed
    input wire mmio_addr, // 1 = 0xFF00 (SW), 0 = 0xFF02 (LW)

    // Internal outputs to datapath
    output reg pc_write, // 1 = update PC, 0 = hold
    output reg pc_src, // 0 = PC++, 1 = branch target
    output reg ir_load, // 1 = load instruction, 0 = hold
    output reg reg_write, // 1 = write register file, 0 = hold
    output reg [3:0] alu_op,
    output reg alu_src, // 0 = register, 1 = immediate
    output reg mem_read,
    output reg mem_write,
    output reg mem_to_reg, // 0 = ALU result, 1 = memory data
    output reg shifter_en,
    output reg counter_en,
    output reg [1:0] shifter_op,

    // External outputs
    output reg out_port_en // latch enable for 16 output pads
);

    // Opcodes (16 total)
    parameter OP_ADD = 4'b0000;
    parameter OP_SUB = 4'b0001;
    parameter OP_AND = 4'b0010;
    parameter OP_OR = 4'b0011;
    parameter OP_XOR = 4'b0100;
    parameter OP_LSL = 4'b0101;
    parameter OP_LSR = 4'b0110;
    parameter OP_MAC = 4'b0111;
    parameter OP_CLZ = 4'b1000;
    parameter OP_BEQ = 4'b1001;
    parameter OP_BNE = 4'b1010;
    parameter OP_LUI = 4'b1011;
    parameter OP_ADDI = 4'b1100;
    parameter OP_LW = 4'b1101;
    parameter OP_SW = 4'b1110;
    parameter OP_HALT = 4'b1111;

    // Shifter operations (4 total)
    parameter SHIFT_LSL = 2'b00;
    parameter SHIFT_LSR = 2'b01;
    parameter SHIFT_MAC = 2'b10;
    parameter SHIFT_CLZ = 2'b11;

    // States (8 total)
    parameter RESET = 3'b000; // 0
    parameter FETCH = 3'b001; // 1
    parameter DECODE = 3'b010; // 2
    parameter EXECUTE = 3'b011; // 3
    parameter MEMORY = 3'b100; // 4
    parameter SHIFT_LOOP = 3'b101; // 5
    parameter WRITEBACK = 3'b110; // 6
    parameter HALT = 3'b111; // 7

    reg [2:0] state;
    reg [2:0] next_state;

    always @(*)
    begin : TRANSITION
        if (rst)
            next_state = RESET;
        else begin
            case (state)
                RESET:
                    next_state = FETCH;

                FETCH:
                    next_state = DECODE;

                DECODE: begin
                    case (opcode)
                        OP_HALT:
                            next_state = HALT;
                        OP_LSL, OP_LSR, OP_MAC, OP_CLZ:
                            next_state = SHIFT_LOOP;
                        default:
                            next_state = EXECUTE;
                    endcase
                end

                EXECUTE: begin
                    case (opcode)
                        OP_BEQ, OP_BNE:
                            next_state = FETCH;
                        OP_LW, OP_SW:
                            next_state = MEMORY;
                        default:
                            next_state = WRITEBACK;
                    endcase
                end

                MEMORY: begin
                    if (opcode == OP_SW)
                        next_state = FETCH;
                    else
                        next_state = WRITEBACK;
                end

                SHIFT_LOOP:
                    next_state = counter_done ? WRITEBACK : SHIFT_LOOP;

                WRITEBACK:
                    next_state = FETCH;

                HALT:
                    next_state = HALT;

                default:
                    next_state = RESET;
            endcase
        end
    end

    always @(negedge clka) 
    begin : SYNC
        if (rst)
            state <= RESET;
        else
            state <= next_state;
    end

    always @(negedge clkb) 
    begin : OUTPUT
        pc_write <= 0;
        pc_src <= 0;
        ir_load <= 0;
        reg_write <= 0;
        alu_op <= 4'b0000;
        alu_src <= 0;
        mem_read <= 0;
        mem_write <= 0;
        mem_to_reg <= 0;
        shifter_en <= 0;
        counter_en <= 0;
        shifter_op <= 2'b00;
        out_port_en <= 0;
        
        case (state)
            RESET, HALT, DECODE: begin
                // Nothing happens
            end

            FETCH: begin
                pc_write <= 1;
                pc_src <= 0; // PC++
                ir_load <= 1;
            end

            EXECUTE: begin
                case (opcode)
                    OP_ADD: begin 
                        alu_op <= OP_ADD;  
                        alu_src <= 0; 
                    end

                    OP_SUB: begin 
                        alu_op <= OP_SUB;  
                        alu_src <= 0; 
                    end

                    OP_AND: begin 
                        alu_op <= OP_AND;  
                        alu_src <= 0; 
                    end

                    OP_OR: begin 
                        alu_op <= OP_OR;   
                        alu_src <= 0; 
                    end

                    OP_XOR: begin 
                        alu_op <= OP_XOR;  
                        alu_src <= 0; 
                    end

                    OP_ADDI: begin 
                        alu_op <= OP_ADD;  
                        alu_src <= 1; 
                    end

                    OP_LUI: begin 
                        alu_op <= OP_LUI;  
                        alu_src <= 1; 
                    end

                    OP_LW: begin 
                        alu_op <= OP_ADD;  
                        alu_src <= 1; 
                    end

                    OP_SW: begin 
                        alu_op <= OP_ADD;  
                        alu_src <= 1; 
                    end

                    OP_BEQ: begin
                        alu_op <= OP_SUB;
                        alu_src <= 0;
                        if (zero_flag) begin // TO EDIT: zero_flag is outputted in next cycle!
                            pc_write <= 1; // TO EDIT: also assert not taken branch case
                            pc_src <= 1;
                        end
                    end

                    OP_BNE: begin
                        alu_op <= OP_SUB;
                        alu_src <= 0;
                        if (~zero_flag) begin // TO EDIT: zero_flag is outputted in next cycle!
                            pc_write <= 1; // TO EDIT: also assert not taken branch case
                            pc_src <= 1;
                        end
                    end

                    default: begin
                        alu_op <= 4'b0000;
                        alu_src <= 0;
                    end
                endcase
            end

            MEMORY: begin
                if (opcode == OP_LW) begin
                    mem_read <= 1;
                end else begin
                    mem_write <= 1;
                    out_port_en <= mmio_addr;
                end
            end

            SHIFT_LOOP: begin
                shifter_en <= 1;
                counter_en <= 1;
                case (opcode)
                    OP_LSL: 
                        shifter_op <= SHIFT_LSL;

                    OP_LSR: 
                        shifter_op <= SHIFT_LSR;

                    OP_MAC: 
                        shifter_op <= SHIFT_MAC;

                    OP_CLZ: 
                        shifter_op <= SHIFT_CLZ;
                        
                    default: 
                        shifter_op <= SHIFT_LSL;
                endcase
            end

            WRITEBACK: begin
                reg_write  <= 1;
                mem_to_reg <= (opcode == OP_LW) ? 1 : 0;
            end
        endcase
    end
endmodule

verif/FSM/control_fsm_tb.v
module control_fsm_tb();
    // Inputs
    reg clka, clkb, rst;
    reg [3:0] opcode;
    reg zero_flag, counter_done, mmio_addr;

    // Outputs
    wire pc_write, pc_src, ir_load, reg_write;
    wire [3:0] alu_op;
    wire alu_src, mem_read, mem_write, mem_to_reg;
    wire shifter_en, counter_en, out_port_en;
    wire [1:0] shifter_op;

    control_fsm U1 (
        .clka(clka), 
        .clkb(clkb), 
        .rst(rst),
        .opcode(opcode), 
        .zero_flag(zero_flag), 
        .counter_done(counter_done), 
        .mmio_addr(mmio_addr),
        .pc_write(pc_write), 
        .pc_src(pc_src), 
        .ir_load(ir_load),
        .reg_write(reg_write), 
        .alu_op(alu_op), 
        .alu_src(alu_src),
        .mem_read(mem_read), 
        .mem_write(mem_write), 
        .mem_to_reg(mem_to_reg),
        .shifter_en(shifter_en), 
        .counter_en(counter_en), 
        .shifter_op(shifter_op), 
        .out_port_en(out_port_en)
    );

    task run_cycle;
    begin
        clka = 0; clkb = 0; #10;
        clka = 1; clkb = 0; #10;
        clka = 0; clkb = 0; #10;
        clka = 0; clkb = 1; #10;
    end
    endtask

    initial begin
        $dumpfile("control_fsm_tb.vcd");
        $dumpvars;

        // System Initialization
        rst = 1; 
        opcode = 4'b0000; 
        zero_flag = 0; 
        counter_done = 0; 
        mmio_addr = 0;
        clka = 0; 
        clkb = 0;
        run_cycle; 
        
        rst = 0;
        run_cycle; // FETCH

        // TEST 1: Standard ALU Instruction (ADD)
        // Flow: FETCH -> DECODE -> EXECUTE -> WRITEBACK -> FETCH
        $display("Testing ADD Instruction.");
        opcode = 4'b0000; // OP_ADD
        run_cycle; // DECODE
        run_cycle; // EXECUTE
        run_cycle; // WRITEBACK
        
        // TEST 2: Multi-Cycle Instruction (MAC)
        // Flow: FETCH -> DECODE -> SHIFT_LOOP (...) -> WRITEBACK
        $display("Testing MAC Instruction.");
        run_cycle; // FETCH
        opcode = 4'b0111; // OP_MAC
        run_cycle; // DECODE
        run_cycle; // SHIFT_LOOP
        
        // Simulate 16-cycle delay with few cycles
        run_cycle; 
        run_cycle; 
        
        // Break the loop
        counter_done = 1; 
        run_cycle; // WRITEBACK
        counter_done = 0;

        // TEST 3: Branch Instruction (BEQ)
        // Flow: FETCH -> DECODE -> EXECUTE -> FETCH
        $display("Testing BEQ Instruction Taken.");
        run_cycle; // FETCH
        opcode = 4'b1001; // OP_BEQ
        zero_flag = 1; // ALU indicates Rs1 == Rs2
        
        run_cycle; // DECODE
        run_cycle; // EXECUTE
        
        zero_flag = 0;
        
        // TEST 4: Store Word MMIO (SW to 0xFF00)
        // Flow: FETCH -> DECODE -> EXECUTE -> MEMORY -> FETCH
        $display("Testing SW Instruction to MMIO.");
        run_cycle; // FETCH
        opcode = 4'b1110; // OP_SW
        mmio_addr = 1; // Target is 0xFF00
        
        run_cycle; // DECODE
        run_cycle; // EXECUTE
        run_cycle; // MEMORY 
        
        mmio_addr = 0;

        
        run_cycle; // FETCH
        run_cycle;

        $display("Simulation Complete.");
        $stop;
    end
endmodule

Questa/control_fsm_tb.vcd
$date
	Mon Mar  2 23:16:09 2026
$end
$version
	QuestaSim Version 2023.2
$end
$timescale
	1ns
$end

$scope module control_fsm_tb $end
$var reg 1 ! clka $end
$var reg 1 " clkb $end
$var reg 1 # rst $end
$var reg 4 $ opcode [3:0] $end
$var reg 1 % zero_flag $end
$var reg 1 & counter_done $end
$var reg 1 ' mmio_addr $end
$var wire 1 ( pc_write $end
$var wire 1 ) pc_src $end
$var wire 1 * ir_load $end
$var wire 1 + reg_write $end
$var wire 1 , alu_op [3] $end
$var wire 1 - alu_op [2] $end
$var wire 1 . alu_op [1] $end
$var wire 1 / alu_op [0] $end
$var wire 1 0 alu_src $end
$var wire 1 1 mem_read $end
$var wire 1 2 mem_write $end
$var wire 1 3 mem_to_reg $end
$var wire 1 4 shifter_en $end
$var wire 1 5 counter_en $end
$var wire 1 6 out_port_en $end
$var wire 1 7 shifter_op [1] $end
$var wire 1 8 shifter_op [0] $end

$scope task run_cycle $end
$upscope $end

$scope module U1 $end
$var parameter 4 9 OP_ADD $end
$var parameter 4 : OP_SUB $end
$var parameter 4 ; OP_AND $end
$var parameter 4 < OP_OR $end
$var parameter 4 = OP_XOR $end
$var parameter 4 > OP_LSL $end
$var parameter 4 ? OP_LSR $end
$var parameter 4 @ OP_MAC $end
$var parameter 4 A OP_CLZ $end
$var parameter 4 B OP_BEQ $end
$var parameter 4 C OP_BNE $end
$var parameter 4 D OP_LUI $end
$var parameter 4 E OP_ADDI $end
$var parameter 4 F OP_LW $end
$var parameter 4 G OP_SW $end
$var parameter 4 H OP_HALT $end
$var parameter 2 I SHIFT_LSL $end
$var parameter 2 J SHIFT_LSR $end
$var parameter 2 K SHIFT_MAC $end
$var parameter 2 L SHIFT_CLZ $end
$var parameter 3 M RESET $end
$var parameter 3 N FETCH $end
$var parameter 3 O DECODE $end
$var parameter 3 P EXECUTE $end
$var parameter 3 Q MEMORY $end
$var parameter 3 R SHIFT_LOOP $end
$var parameter 3 S WRITEBACK $end
$var parameter 3 T HALT $end
$var wire 1 U clka $end
$var wire 1 V clkb $end
$var wire 1 W rst $end
$var wire 1 X opcode [3] $end
$var wire 1 Y opcode [2] $end
$var wire 1 Z opcode [1] $end
$var wire 1 [ opcode [0] $end
$var wire 1 \ zero_flag $end
$var wire 1 ] counter_done $end
$var wire 1 ^ mmio_addr $end
$var reg 1 _ pc_write $end
$var reg 1 ` pc_src $end
$var reg 1 a ir_load $end
$var reg 1 b reg_write $end
$var reg 4 c alu_op [3:0] $end
$var reg 1 d alu_src $end
$var reg 1 e mem_read $end
$var reg 1 f mem_write $end
$var reg 1 g mem_to_reg $end
$var reg 1 h shifter_en $end
$var reg 1 i counter_en $end
$var reg 2 j shifter_op [1:0] $end
$var reg 1 k out_port_en $end
$var reg 3 l state [2:0] $end
$var reg 3 m next_state [2:0] $end

$scope begin TRANSITION $end
$upscope $end

$scope begin SYNC $end
$upscope $end

$scope begin OUTPUT $end
$upscope $end
$upscope $end
$upscope $end
$enddefinitions $end
#0
$dumpvars
0!
0"
1#
b0 $
0%
0&
0'
0_
0`
0a
0b
b0 c
0d
0e
0f
0g
0h
0i
b0 j
0k
b0 l
b0 m
b0 9
b1 :
b10 ;
b11 <
b100 =
b101 >
b110 ?
b111 @
b1000 A
b1001 B
b1010 C
b1011 D
b1100 E
b1101 F
b1110 G
b1111 H
b0 I
b1 J
b10 K
b11 L
b0 M
b1 N
b10 O
b11 P
b100 Q
b101 R
b110 S
b111 T
0(
0)
0*
0+
0/
0.
0-
0,
00
01
02
03
04
05
06
08
07
0^
0]
0\
0[
0Z
0Y
0X
1W
0V
0U
$end
#10
1!
1U
#20
0!
0U
#30
1"
1V
#40
0#
0"
0W
0V
b1 m
#50
1!
1U
#60
0!
0U
b1 l
b10 m
#70
1"
1V
#80
0"
0V
1_
1a
1(
1*
#90
1!
1U
#100
0!
0U
b10 l
b11 m
#110
1"
1V
#120
0"
0V
0_
0a
0(
0*
#130
1!
1U
#140
0!
0U
b11 l
b110 m
#150
1"
1V
#160
0"
0V
#170
1!
1U
#180
0!
0U
b110 l
b1 m
#190
1"
1V
#200
0"
0V
1b
1+
#210
1!
1U
#220
0!
0U
b1 l
b10 m
#230
1"
1V
#240
b111 $
0"
1[
1Z
1Y
0V
0b
1_
1a
0+
1(
1*
#250
1!
1U
#260
0!
0U
b10 l
b101 m
#270
1"
1V
#280
0"
0V
0_
0a
0(
0*
#290
1!
1U
#300
0!
0U
b101 l
#310
1"
1V
#320
0"
0V
1h
1i
b10 j
14
15
17
#330
1!
1U
#340
0!
0U
#350
1"
1V
#360
0"
0V
0h
0i
b0 j
1h
1i
b10 j
#370
1!
1U
#380
0!
0U
#390
1"
1V
#400
1&
0"
1]
0V
b110 m
0h
0i
b0 j
1h
1i
b10 j
#410
1!
1U
#420
0!
0U
b110 l
b1 m
#430
1"
1V
#440
0&
0"
0]
0V
0h
0i
b0 j
1b
04
05
07
1+
#450
1!
1U
#460
0!
0U
b1 l
b10 m
#470
1"
1V
#480
b1001 $
1%
0"
1\
0Z
0Y
1X
0V
0b
1_
1a
0+
1(
1*
#490
1!
1U
#500
0!
0U
b10 l
b11 m
#510
1"
1V
#520
0"
0V
0_
0a
0(
0*
#530
1!
1U
#540
0!
0U
b11 l
b1 m
#550
1"
1V
#560
0%
0"
0\
0V
b1 c
1/
#570
1!
1U
#580
0!
0U
b1 l
b10 m
#590
1"
1V
#600
b1110 $
1'
0"
1^
0[
1Z
1Y
0V
b0 c
1_
1a
0/
1(
1*
#610
1!
1U
#620
0!
0U
b10 l
b11 m
#630
1"
1V
#640
0"
0V
0_
0a
0(
0*
#650
1!
1U
#660
0!
0U
b11 l
b100 m
#670
1"
1V
#680
0"
0V
1d
10
#690
1!
1U
#700
0!
0U
b100 l
b1 m
#710
1"
1V
#720
0'
0"
0^
0V
0d
1f
00
12
#730
1!
1U
#740
0!
0U
b1 l
b10 m
#750
1"
1V
#760
0"
0V
0f
1_
1a
02
1(
1*
#770
1!
1U
#780
0!
0U
b10 l
b11 m
